pystaffo/__init__.py
pystaffo/cached.py
pystaffo/paginated.py
pystaffo/requestors.py
pystaffo/staffo.py
PyStaffo-0.1.2.dist-info/LICENSE.md
PyStaffo-0.1.2.dist-info/METADATA
PyStaffo-0.1.2.dist-info/WHEEL
PyStaffo-0.1.2.dist-info/top_level.txt
PyStaffo-0.1.2.dist-info/RECORD
