Metadata-Version: 2.1
Name: PyStaffo
Version: 0.1.2
Summary: A Staffomatic API Python wrapper
Home-page: http://github.com/perrydunn/PyStaffo
Author: Peregrine Dunn
Author-email: perrydunn@hotmail.co.uk
License: MIT
Platform: UNKNOWN
Classifier: Development Status :: 4 - Beta
Classifier: License :: OSI Approved :: MIT License
Classifier: Natural Language :: English
Classifier: Programming Language :: Python :: 3
Classifier: Topic :: Office/Business :: Scheduling
Requires-Dist: pytz
Requires-Dist: requests (>=2.4.2)
